{
  "categories": [
    {
      "id": "cat_1783625908993",
      "name": "Alwan Sport",
      "image": "https://safiafamily.com/uploads/family/alwan/Alwan_Ryazya_1.png",
      "order": 0
    }
  ],
  "channels": [
    {
      "id": "ch_1783626536192",
      "categoryId": "cat_1783625908993",
      "name": "Alwan Sport 7 4k",
      "url": "http://myhand.org:8080/live/Hussain879/16318166709566/921302.m3u8",
      "image": "https://safiafamily.com/uploads/family/alwan/Alwan_Ryazya_4.png",
      "order": 6
    },
    {
      "id": "ch_1783626723756",
      "categoryId": "cat_1783625908993",
      "name": "Alwan Sport  HD 2",
      "url": "http://myhand.org:8080/live/Hussain879/16318166709566/847439.m3u8",
      "image": "https://safiafamily.com/uploads/family/alwan/Alwan_Ryazya_5.png",
      "order": 8
    },
    {
      "id": "ch_1783626744354",
      "categoryId": "cat_1783625908993",
      "name": "Alwan Sport  HD 3",
      "url": "http://myhand.org:8080/live/Hussain879/16318166709566/847440.m3u8",
      "image": "https://safiafamily.com/uploads/family/alwan/Alwan_Ryazya_5.png",
      "order": 9
    },
    {
      "id": "ch_1783626764477",
      "categoryId": "cat_1783625908993",
      "name": "Alwan Sport  HD 4",
      "url": "http://myhand.org:8080/live/Hussain879/16318166709566/847441.m3u8",
      "image": "https://safiafamily.com/uploads/family/alwan/Alwan_Ryazya_5.png",
      "order": 10
    },
    {
      "id": "ch_1783626791198",
      "categoryId": "cat_1783625908993",
      "name": "Alwan Sport  HD 5",
      "url": "http://myhand.org:8080/live/Hussain879/16318166709566/847442.m3u8",
      "image": "https://safiafamily.com/uploads/family/alwan/Alwan_Ryazya_5.png",
      "order": 11
    },
    {
      "id": "ch_1783626817187",
      "categoryId": "cat_1783625908993",
      "name": "Alwan Sport  HD 6",
      "url": "http://myhand.org:8080/live/Hussain879/16318166709566/847443.m3u8",
      "image": "https://safiafamily.com/uploads/family/alwan/Alwan_Ryazya_5.png",
      "order": 12
    },
    {
      "id": "ch_1783627180101",
      "categoryId": "cat_1783625908993",
      "name": "Alwan Sport   SD 1",
      "url": "http://myhand.org:8080/live/Hussain879/16318166709566/847444.m3u8",
      "image": "https://safiafamily.com/uploads/family/alwan/Alwan_Ryazya_5.png",
      "order": 13
    },
    {
      "id": "ch_1783627263811",
      "categoryId": "cat_1783625908993",
      "name": "Alwan Sport   SD 2",
      "url": "http://myhand.org:8080/live/Hussain879/16318166709566/847445.m3u8",
      "image": "https://safiafamily.com/uploads/family/alwan/Alwan_Ryazya_2.png",
      "order": 14
    },
    {
      "id": "ch_1783711665568",
      "categoryId": "cat_1783625908993",
      "name": "بث  4k",
      "url": "http://marveliptv.life:80/live/35700753466/35708754677/530867.m3u8",
      "image": "https://placehold.co/40x40/1e293b/38bdf8?text=CH",
      "order": 14
    },
    {
      "id": "ch_1783627279677",
      "categoryId": "cat_1783625908993",
      "name": "Alwan Sport   SD 3",
      "url": "http://myhand.org:8080/live/Hussain879/16318166709566/847446.m3u8",
      "image": "https://safiafamily.com/uploads/family/alwan/Alwan_Ryazya_3.png",
      "order": 15
    },
    {
      "id": "ch_1783711705152",
      "categoryId": "cat_1783625908993",
      "name": "بث تجريبي HD",
      "url": "http://marveliptv.life:80/live/35700753466/35708754677/528744.m3u8",
      "image": "https://placehold.co/40x40/1e293b/38bdf8?text=CH",
      "order": 15
    },
    {
      "id": "ch_1783627306368",
      "categoryId": "cat_1783625908993",
      "name": "Alwan Sport   SD 4",
      "url": "http://myhand.org:8080/live/Hussain879/16318166709566/847446.m3u8",
      "image": "https://safiafamily.com/uploads/family/alwan/Alwan_Ryazya_4.png",
      "order": 16
    },
    {
      "id": "ch_1783711724467",
      "categoryId": "cat_1783625908993",
      "name": "بث تجريبي SD",
      "url": "http://marveliptv.life:80/live/35700753466/35708754677/528738.m3u8\"",
      "image": "https://placehold.co/40x40/1e293b/38bdf8?text=CH",
      "order": 16
    },
    {
      "id": "ch_1783627339103",
      "categoryId": "cat_1783625908993",
      "name": "Alwan Sport   SD 5",
      "url": "http://myhand.org:8080/live/Hussain879/16318166709566/847448.m3u8",
      "image": "https://safiafamily.com/uploads/family/alwan/Alwan_Ryazya_5.png",
      "order": 17
    }
  ]
}